fastapi_booster/Auth/Oauth/__init__.py
fastapi_booster/Auth/__init__.py
fastapi_booster/Auth/httpBasic/__init__.py
fastapi_booster/Auth/jwt/__init__.py
fastapi_booster/CertManager/__init__.py
fastapi_booster/CertManager/schemas.py
fastapi_booster/LifeSpanManager/__init__.py
fastapi_booster/Module/__init__.py
fastapi_booster/ModuleManager/__init__.py
fastapi_booster/UserManager/__init__.py
fastapi_booster/__init__.py
fastapi_booster-0.2.1.dist-info/LICENSE
fastapi_booster-0.2.1.dist-info/METADATA
fastapi_booster-0.2.1.dist-info/WHEEL
fastapi_booster-0.2.1.dist-info/RECORD
