Metadata-Version: 2.1
Name: fastapi-booster
Version: 0.2.1
Summary: 
Home-page: https://github.com/ulfaric/FastAPI-Booster
License: CC-BY-NC-ND-4.0
Author: ulfaric
Author-email: ryf0510@live.com
Requires-Python: >=3.10,<4.0
Classifier: License :: Other/Proprietary License
Classifier: Programming Language :: Python :: 3
Classifier: Programming Language :: Python :: 3.10
Classifier: Programming Language :: Python :: 3.11
Classifier: Programming Language :: Python :: 3.12
Classifier: Programming Language :: Python :: 3.13
Requires-Dist: akatosh (>=3.1.6,<4.0.0)
Requires-Dist: authlib (>=1.3.2,<2.0.0)
Requires-Dist: bcrypt (==4.0.1)
Requires-Dist: colorlog (>=6.8.2,<7.0.0)
Requires-Dist: cryptography (>=43.0.1,<44.0.0)
Requires-Dist: fastapi[all] (>=0.112.1,<0.113.0)
Requires-Dist: opentelemetry-api (>=1.28.1,<2.0.0)
Requires-Dist: opentelemetry-exporter-otlp (>=1.28.1,<2.0.0)
Requires-Dist: opentelemetry-instrumentation-fastapi (>=0.49b1,<0.50)
Requires-Dist: opentelemetry-sdk (>=1.28.1,<2.0.0)
Requires-Dist: passlib[bcrypt] (>=1.7.4,<2.0.0)
Requires-Dist: psycopg2-binary (>=2.9.10,<3.0.0)
Requires-Dist: pyjwt (>=2.9.0,<3.0.0)
Requires-Dist: sqlalchemy (>=2.0.32,<3.0.0)
Project-URL: Repository, https://github.com/ulfaric/FastAPI-Booster
